setup.cfg
setup.py
django_macfly/__init__.py
django_macfly.egg-info/PKG-INFO
django_macfly.egg-info/SOURCES.txt
django_macfly.egg-info/dependency_links.txt
django_macfly.egg-info/pbr.json
django_macfly.egg-info/top_level.txt
django_macfly/management/__init__.py
django_macfly/management/commands/__init__.py
django_macfly/management/commands/sqlmigratefwd.py