Metadata-Version: 1.1
Name: django-macfly
Version: 0.4.1
Summary: Django helpers to run SQL schema migrations ahead of time.
Home-page: https://github.com/novafloss/django-MacFly
Author: Bruno Dupuis
Author-email: bruno.dupuis@people-doc.com
License: UNKNOWN
Download-URL: https://github.com/novafloss/django-MacFly/tarball/0.4.1
Keywords: django,migrations,DBA
Platform: UNKNOWN
